livemetrics/__init__.py
livemetrics/metrics.py
livemetrics/dashboard/dashboard.html
livemetrics/dashboard/dashboard.py
livemetrics/publishers/aiohttp.py
livemetrics/publishers/django.py
livemetrics/publishers/flask.py
livemetrics/publishers/http.py
livemetrics-0.7.1.dist-info/AUTHORS.rst
livemetrics-0.7.1.dist-info/LICENSE
livemetrics-0.7.1.dist-info/METADATA
livemetrics-0.7.1.dist-info/WHEEL
livemetrics-0.7.1.dist-info/entry_points.txt
livemetrics-0.7.1.dist-info/top_level.txt
livemetrics-0.7.1.dist-info/RECORD
