Metadata-Version: 2.1
Name: livemetrics
Version: 0.7.1
Summary: LiveMetrics collector and publisher for Python applications
Home-page: https://github.com/idemia/python-livemetrics
Author: attr: livemetrics.__author__
Author-email: olivier.heurtier@idemia.com
License: CeCILL-C
Classifier: Development Status :: 4 - Beta
Classifier: Programming Language :: Python :: 3.8
Classifier: Programming Language :: Python :: 3.9
Classifier: Programming Language :: Python :: 3.10
Classifier: Programming Language :: Python :: 3.11
Classifier: Programming Language :: Python :: 3.12
Classifier: License :: CeCILL-C Free Software License Agreement (CECILL-C)
Requires-Python: >=3.8
License-File: LICENSE
License-File: AUTHORS.rst
Provides-Extra: aiohttp
Requires-Dist: aiohttp ; extra == 'aiohttp'
Provides-Extra: dashboard
Requires-Dist: jinja2 ; extra == 'dashboard'
Requires-Dist: PyYAML ; extra == 'dashboard'
Requires-Dist: aiohttp ; extra == 'dashboard'
Provides-Extra: django
Requires-Dist: django ; extra == 'django'
Provides-Extra: flask
Requires-Dist: flask ; extra == 'flask'
